googlecloudfunctions/__init__.py
google_cloud_functions_utils-0.3.6.dist-info/LICENSE
google_cloud_functions_utils-0.3.6.dist-info/METADATA
google_cloud_functions_utils-0.3.6.dist-info/WHEEL
google_cloud_functions_utils-0.3.6.dist-info/top_level.txt
google_cloud_functions_utils-0.3.6.dist-info/RECORD
